PerfectoLibrary/__init__.py
PerfectoLibrary/version.py
PerfectoLibrary/keywords/__init__.py
PerfectoLibrary/keywords/_devices.py
PerfectoLibrary/keywords/_general.py
PerfectoLibrary/keywords/_rest_acts.py
PerfectoLibrary/keywords/keywordgroup.py
PerfectoLibrary/listeners/__init__.py
PerfectoLibrary/listeners/_perfectoListener.py
perfectolibrary_py37-0.5.2.dist-info/METADATA
perfectolibrary_py37-0.5.2.dist-info/WHEEL
perfectolibrary_py37-0.5.2.dist-info/top_level.txt
perfectolibrary_py37-0.5.2.dist-info/RECORD
